unsubmail/__init__.py
unsubmail/command.py
unsubmail/config.py
unsubmail/http.py
unsubmail/imap.py
unsubmail-1.0.0.dist-info/METADATA
unsubmail-1.0.0.dist-info/WHEEL
unsubmail-1.0.0.dist-info/entry_points.txt
unsubmail-1.0.0.dist-info/top_level.txt
unsubmail-1.0.0.dist-info/zip-safe
unsubmail-1.0.0.dist-info/RECORD
