Metadata-Version: 2.1
Name: unsubmail
Version: 1.0.0
Summary: UNKNOWN
Home-page: https://github.com/jdcasey/unsubmail
Author: John Casey
Author-email: jdcasey@commonjava.org
License: GPLv3+
Keywords: imap spam
Platform: UNKNOWN
Classifier: Development Status :: 3 - Alpha
Classifier: Intended Audience :: Developers
Classifier: License :: OSI Approved :: GNU General Public License (GPL)
Classifier: Programming Language :: Python :: 3
Requires-Dist: ruamel.yaml
Requires-Dist: click
Requires-Dist: requests
Requires-Dist: beautifulsoup4
